pylux/__init__.py
pylux/__main__.py
pylux/clihelper.py
pylux/default.conf
pylux/document.py
pylux/reference.py
pylux/interface/__init__.py
pylux/interface/cli.py
pylux/interface/fallback.py
pylux/interpreter/__init__.py
pylux/interpreter/base.py
pylux/interpreter/eos.py
pylux/interpreter/help.py
pylux/interpreter/plot.py
pylux/interpreter/report.py
pylux/interpreter/template.py
pylux/lib/__init__.py
pylux/lib/autocomplete.py
pylux/lib/constant.py
pylux/lib/data.py
pylux/lib/exception.py
pylux/lib/plothelper.py
pylux/lib/polygon.py
pylux/lib/printer.py
pylux/lib/tagger.py
pylux-1.0.dist-info/COPYING
pylux-1.0.dist-info/METADATA
pylux-1.0.dist-info/WHEEL
pylux-1.0.dist-info/entry_points.txt
pylux-1.0.dist-info/top_level.txt
pylux-1.0.dist-info/RECORD
