Metadata-Version: 2.1
Name: pylux
Version: 1.0
Summary: Program for creating stage and entertainment lighting documentation
Home-page: https://github.com/jackdpage/pylux
Author: Jack Page
Author-email: jdpboc98@gmail.com
License: UNKNOWN
Platform: UNKNOWN
Requires-Dist: urwid
Requires-Dist: jinja2
Requires-Dist: numpy
Requires-Dist: pygdtf
